blueprint/__init__.py
blueprint/_version.py
blueprint/base.py
blueprint/collection.py
blueprint/dice.py
blueprint/factories.py
blueprint/fields.py
blueprint/markov.py
blueprint/mods.py
blueprint/taggables.py
python_blueprint-0.7.dist-info/METADATA
python_blueprint-0.7.dist-info/WHEEL
python_blueprint-0.7.dist-info/licenses/LICENSE.md
python_blueprint-0.7.dist-info/RECORD
