Metadata-Version: 2.4
Name: python-blueprint
Version: 0.7
Summary: Magical blueprints for procedural generation of content.
Project-URL: Homepage, https://github.com/eykd/blueprint
Project-URL: Issues, https://github.com/eykd/blueprint/issues
Project-URL: Repository, https://github.com/eykd/blueprint
Author-email: David Eyk <david@worldsenoughstudios.com>
License-Expression: MIT
License-File: LICENSE.md
Classifier: Development Status :: 4 - Beta
Classifier: Environment :: Console
Classifier: Intended Audience :: Developers
Classifier: License :: OSI Approved :: MIT License
Classifier: Operating System :: OS Independent
Classifier: Programming Language :: Python
Classifier: Programming Language :: Python :: 3
Classifier: Topic :: Artistic Software
Classifier: Topic :: Games/Entertainment
Requires-Python: >=3.11
